tucao/__init__.py
tucao/tucao.py
tucao-0.0.1.dist-info/DESCRIPTION.rst
tucao-0.0.1.dist-info/METADATA
tucao-0.0.1.dist-info/RECORD
tucao-0.0.1.dist-info/WHEEL
tucao-0.0.1.dist-info/entry_points.txt
tucao-0.0.1.dist-info/metadata.json
tucao-0.0.1.dist-info/top_level.txt
